{
  "$schema": "http://json-schema.org/draft-04/schema#",
  "type": "array",
  "items": {
    "type": "object",
    "properties": {
      "id": {
        "type": "number"
      },
      "name": {
        "type": "string"
      },
      "profession": {
        "type": "string"
      },
      "elite": {
        "type": "boolean"
      },
      "minor_traits": {
        "type": "array",
        "items": {
          "type": "number"
        }
      },
      "major_traits": {
        "type": "array",
        "items": {
          "type": "number"
        }
      },
      "icon": {
        "type": "string"
      },
      "background": {
        "type": "string"
      },
      "weapon_trait": {
        "type": "number"
      },
      "profession_icon_big": {
        "type": "string"
      },
      "profession_icon": {
        "type": "string"
      }
    },
    "required": [
      "id",
      "name",
      "profession",
      "elite",
      "minor_traits",
      "major_traits",
      "icon",
      "background"
    ]
  },
  "properties": {},
  "additionalProperties": false
}